fr8/__init__.py
fr8/location.py
fr8-0.0.5.dist-info/METADATA
fr8-0.0.5.dist-info/WHEEL
fr8-0.0.5.dist-info/RECORD
